hrfh/__init__.py
hrfh/__main__.py
hrfh/assets/json/akamai/2.17.56.198.json
hrfh/assets/json/akamai/23.10.76.87.json
hrfh/assets/json/akamai/23.15.29.107.json
hrfh/assets/json/akamai/23.2.228.166.json
hrfh/assets/json/akamai/23.33.232.126.json
hrfh/assets/json/akamai/23.37.16.46.json
hrfh/assets/json/akamai/23.37.41.10.json
hrfh/assets/json/alibaba-cdn/1.31.128.204.json
hrfh/assets/json/alibaba-cdn/27.221.119.214.json
hrfh/assets/json/alibaba-cdn/47.105.29.111.json
hrfh/assets/json/alibaba-cdn/47.246.0.212.json
hrfh/assets/json/alibaba-cdn/47.246.2.86.json
hrfh/assets/json/alibaba-cdn/47.89.66.194.json
hrfh/assets/json/alibaba-cdn/8.45.52.202.json
hrfh/assets/json/alibaba-cdn/8.45.52.239.json
hrfh/assets/json/alibaba-cdn/8.45.52.243.json
hrfh/assets/json/alibaba-dcdn/116.136.183.110.json
hrfh/assets/json/alibaba-dcdn/117.21.229.224.json
hrfh/assets/json/alibaba-dcdn/117.21.229.244.json
hrfh/assets/json/alibaba-dcdn/117.68.76.116.json
hrfh/assets/json/alibaba-dcdn/117.68.76.71.json
hrfh/assets/json/alibaba-dcdn/119.188.120.239.json
hrfh/assets/json/alibaba-waf/39.96.126.169.json
hrfh/assets/json/alibaba-waf/39.96.126.46.json
hrfh/assets/json/alibaba-waf/39.96.126.77.json
hrfh/assets/json/alibaba-waf/8.139.72.161.json
hrfh/assets/json/alibaba-waf/8.139.72.165.json
hrfh/assets/json/alibaba-waf/8.139.72.182.json
hrfh/assets/json/alibaba-waf/8.139.74.175.json
hrfh/assets/json/alibaba-waf/8.139.74.183.json
hrfh/assets/json/alibaba-waf/8.139.74.190.json
hrfh/assets/json/alibaba-waf/8.139.74.191.json
hrfh/assets/json/baidu/1.194.253.41.json
hrfh/assets/json/baidu/27.221.77.41.json
hrfh/assets/json/baidu/36.99.225.41.json
hrfh/assets/json/baidu/42.101.4.41.json
hrfh/assets/json/baidu/42.101.56.41.json
hrfh/assets/json/baidu/42.81.98.41.json
hrfh/assets/json/baidu/58.222.20.41.json
hrfh/assets/json/baidu/58.42.14.41.json
hrfh/assets/json/baidu/58.57.102.41.json
hrfh/assets/json/huawei/23.251.120.79.json
hrfh/assets/json/huawei/23.251.120.87.json
hrfh-0.1.22.dist-info/METADATA
hrfh-0.1.22.dist-info/WHEEL
hrfh-0.1.22.dist-info/entry_points.txt
hrfh-0.1.22.dist-info/top_level.txt
hrfh-0.1.22.dist-info/RECORD
