Metadata-Version: 2.4
Name: hrfh
Version: 0.1.22
Summary: HTTP Response Fuzzy Hashing
Requires-Python: >=3.7
Requires-Dist: bs4>=0.0.2
Requires-Dist: http-parse>=0.1.5
Requires-Dist: nltk>=3.8.1
Requires-Dist: ppdeep>=20250625
Requires-Dist: structlog>=23.1.0
Requires-Dist: typer>=0.16.0
